mountwizzard3
