Metadata-Version: 1.2
Name: mountwizzard3
Version: 3.0rc5
Summary: tooling for a 10micron mount
Home-page: https://github.com/mworion/MountWizzard3-DIST
Author: mw
Author-email: michael@wuertenberger.org
License: APL 2.0
Platform: UNKNOWN
Requires-Python: ~=3.6.3
